{
  "code": 200,
  "msg": "查询成功",
  "data": {
    "fCircuitid": "101000060001",
    "fCircuitname": "10kV进线",
    "monthValueListUpToNow": [
      {
        "fSubid": 10100006,
        "fCircuitid": "101000060001",
        "fDate": "2024-01-01",
        "fDayvalue": 758536.25
      },
      {
        "fSubid": 10100006,
        "fCircuitid": "101000060001",
        "fDate": "2024-02-01",
        "fDayvalue": 543496.0
      },
      {
        "fSubid": 10100006,
        "fCircuitid": "101000060001",
        "fDate": "2024-03-01",
        "fDayvalue": 606615.75
      },
      {
        "fSubid": 10100006,
        "fCircuitid": "101000060001",
        "fDate": "2024-04-01",
        "fDayvalue": 582608.5
      },
      {
        "fSubid": 10100006,
        "fCircuitid": "101000060001",
        "fDate": "2024-05-01",
        "fDayvalue": 402807.5
      },
      {
        "fSubid": 10100006,
        "fCircuitid": "101000060001",
        "fDate": "2024-06-01",
        "fDayvalue": 1074112.0
      },
      {
        "fSubid": 10100006,
        "fCircuitid": "101000060001",
        "fDate": "2024-07-01",
        "pervalue": 430631.95
      },
      {
        "fSubid": 10100006,
        "fCircuitid": "101000060001",
        "fDate": "2024-08-01",
        "pervalue": 455441.21
      },
      {
        "fSubid": 10100006,
        "fCircuitid": "101000060001",
        "fDate": "2024-09-01",
        "pervalue": 357686.82
      },
      {
        "fSubid": 10100006,
        "fCircuitid": "101000060001",
        "fDate": "2024-10-01",
        "pervalue": 325511.43
      },
      {
        "fSubid": 10100006,
        "fCircuitid": "101000060001",
        "fDate": "2024-11-01",
        "pervalue": 382046.77
      },
      {
        "fSubid": 10100006,
        "fCircuitid": "101000060001",
        "fDate": "2024-12-01",
        "pervalue": 550703.75
      }
    ]
  }
}
